ekfsm/__init__.py
ekfsm/cli.py
ekfsm/config.py
ekfsm/exceptions.py
ekfsm/lock.py
ekfsm/log.py
ekfsm/py.typed
ekfsm/simctrl.py
ekfsm/system.py
ekfsm/utils.py
ekfsm/boards/oem/ekf/ccu.yaml
ekfsm/boards/oem/ekf/sc5-festival.yaml
ekfsm/boards/oem/ekf/sc9-toccata.yaml
ekfsm/boards/oem/ekf/se5-club.yaml
ekfsm/boards/oem/ekf/sn4-djembe.yaml
ekfsm/boards/oem/ekf/spv-mystic.yaml
ekfsm/boards/oem/ekf/sq1-track.yaml
ekfsm/boards/oem/ekf/sq3-quartet.yaml
ekfsm/boards/oem/ekf/srf-fan.yaml
ekfsm/boards/oem/ekf/sur-uart.yaml
ekfsm/boards/oem/ekf/z1010.yaml
ekfsm/boards/oem/hitron/hdrc-300s.yaml
ekfsm/core/__init__.py
ekfsm/core/components.py
ekfsm/core/connections.py
ekfsm/core/probe.py
ekfsm/core/slots.py
ekfsm/core/sysfs.py
ekfsm/core/utils.py
ekfsm/devices/__init__.py
ekfsm/devices/button.py
ekfsm/devices/buttonArray.py
ekfsm/devices/colorLed.py
ekfsm/devices/coretemp.py
ekfsm/devices/eeprom.py
ekfsm/devices/ekf_ccu_uc.py
ekfsm/devices/ekf_sur_led.py
ekfsm/devices/generic.py
ekfsm/devices/gpio.py
ekfsm/devices/iio.py
ekfsm/devices/iio_thermal_humidity.py
ekfsm/devices/imu.py
ekfsm/devices/io4edge.py
ekfsm/devices/ledArray.py
ekfsm/devices/mux.py
ekfsm/devices/pixelDisplay.py
ekfsm/devices/pmbus.py
ekfsm/devices/smbios.py
ekfsm/devices/smbus.py
ekfsm/devices/thermal_humidity.py
ekfsm/devices/utils.py
ekfsm/devices/watchdog.py
ekfsm-1.4.0.dist-info/METADATA
ekfsm-1.4.0.dist-info/WHEEL
ekfsm-1.4.0.dist-info/entry_points.txt
ekfsm-1.4.0.dist-info/RECORD
