Metadata-Version: 2.4
Name: ekfsm
Version: 1.4.0
Summary: The EKF System Management Library (ekfsm) is a sensor monitoring suite for Compact PCI Serial devices.
Author-email: Jan Jansen <jan@ekf.de>, Klaus Popp <klaus.popp@ci4rail.com>, Felix Päßler <fp@ekf.de>
Requires-Python: >=3.12
Requires-Dist: anytree
Requires-Dist: click>=8.0.1
Requires-Dist: crcmod
Requires-Dist: gpiod>=2.1.0
Requires-Dist: hexdump
Requires-Dist: io4edge-client>=2.0.3
Requires-Dist: ipdb>=0.13.13
Requires-Dist: more-itertools
Requires-Dist: munch
Requires-Dist: pillow
Requires-Dist: protobuf>=6.32.1
Requires-Dist: schema>=0.7.7
Requires-Dist: smbus2
Requires-Dist: termcolor>=3.0.1
Requires-Dist: types-pyyaml>=6.0.12.20241230
Requires-Dist: yamale
